pathins/__init__.py
pathins/__main__.py
pathins/bezier.py
pathins/bridge.py
pathins/contours.py
pathins/coordinates.py
pathins/datastructures.py
pathins/direction.py
pathins/math.py
pathins/path.py
pathins/segments.py
pathins/stringbuilder.py
pathins/utils.py
pathins/validators.py
pathins-0.5.4.dist-info/LICENSE
pathins-0.5.4.dist-info/METADATA
pathins-0.5.4.dist-info/WHEEL
pathins-0.5.4.dist-info/entry_points.txt
pathins-0.5.4.dist-info/top_level.txt
pathins-0.5.4.dist-info/RECORD
