Metadata-Version: 2.1
Name: pathins
Version: 0.5.4
Summary: Quadratic font curve path inspector
Home-page: https://github.com/source-foundry/path-inspector
Author: Chris Simpkins
Author-email: chris@sourcefoundry.org
License: Apache License v2.0
Platform: Any
Classifier: Development Status :: 4 - Beta
Classifier: Environment :: Console
Classifier: Intended Audience :: Developers
Classifier: Intended Audience :: End Users/Desktop
Classifier: License :: OSI Approved :: Apache Software License
Classifier: Natural Language :: English
Classifier: Operating System :: OS Independent
Classifier: Programming Language :: Python
Classifier: Programming Language :: Python :: 3
Classifier: Programming Language :: Python :: 3.6
Classifier: Programming Language :: Python :: 3.7
Classifier: Programming Language :: Python :: 3.8
Classifier: Programming Language :: Python :: 3.9
Requires-Python: >=3.6.0
Requires-Dist: skia-pathops (>=0.5.1.post1)
Requires-Dist: cython (>=0.29.21)
Requires-Dist: fontTools (>=4.15.0)
Provides-Extra: dev
Requires-Dist: coverage ; extra == 'dev'
Requires-Dist: pytest ; extra == 'dev'
Requires-Dist: tox ; extra == 'dev'
Requires-Dist: flake8 ; extra == 'dev'
Requires-Dist: mypy ; extra == 'dev'
Provides-Extra: maintain
Requires-Dist: wheel ; extra == 'maintain'
Requires-Dist: setuptools ; extra == 'maintain'
Requires-Dist: twine ; extra == 'maintain'
